README.rst
setup.cfg
setup.py
pycrsx/__init__.py
pycrsx/loader.py
pycrsx/parser.py
pycrsx/utils.py
pycrsx.egg-info/PKG-INFO
pycrsx.egg-info/SOURCES.txt
pycrsx.egg-info/dependency_links.txt
pycrsx.egg-info/top_level.txt
pycrsx/elements/__init__.py
pycrsx/elements/containers.py
pycrsx/elements/datums.py
pycrsx/elements/directions.py
pycrsx/elements/ellipsoids.py
pycrsx/elements/parameters.py
pycrsx/elements/projections.py
pycrsx/elements/units.py
pycrsx/elements/__init__.py
pycrsx/elements/containers.py
pycrsx/elements/datums.py
pycrsx/elements/directions.py
pycrsx/elements/ellipsoids.py
pycrsx/elements/parameters.py
pycrsx/elements/projections.py
pycrsx/elements/units.py