Metadata-Version: 1.1
Name: pycrsx
Version: 1.0.2
Summary: GIS package for reading, writing, and converting between CRS formats.
Home-page: https://github.com/mullenkamp/PyCRSx
Author: Mike Kittridge
Author-email: mullenkamp1@gmail.com
License: MIT
Keywords: GIS spatial CRS coordinates format
Platform: UNKNOWN
Classifier: Development Status :: 3 - Alpha
Classifier: Intended Audience :: Developers
Classifier: Topic :: Software Development :: Build Tools
Classifier: License :: OSI Approved :: Apache Software License
Classifier: Programming Language :: Python :: 2
Classifier: Programming Language :: Python :: 2.7
Classifier: Programming Language :: Python :: 3
Classifier: Programming Language :: Python :: 3.4
Classifier: Programming Language :: Python :: 3.5
Classifier: Programming Language :: Python :: 3.6
